pyscilog/__init__.py
pyscilog/color.py
pyscilog/filter.py
pyscilog/handlers.py
pyscilog/state.py
pyscilog/verbosity.py
pyscilog/wrapper.py
pyscilog/writer.py
test/__init__.py
test/test_main.py
pyscilog-0.1.2.dist-info/LICENSE
pyscilog-0.1.2.dist-info/METADATA
pyscilog-0.1.2.dist-info/WHEEL
pyscilog-0.1.2.dist-info/top_level.txt
pyscilog-0.1.2.dist-info/RECORD
